{
  "version": "1.0.0",
  "timestamp": 1763442039985,
  "workspaceRoot": "/home/dtech/VCF/Blog",
  "registries": {
    "components": {
      "components": [
        [
          "__phoenix_builtins__",
          [
            {
              "name": "link",
              "moduleName": "Phoenix.Component",
              "filePath": "/home/dtech/.vscode/extensions/onsever.phoenix-pulse-1.3.0/node_modules/@phoenix-pulse/language-server/resources/phoenix_component_builtins.ex",
              "line": 1,
              "doc": "Phoenix.Component.link/1 – Generates an anchor tag that supports LiveView-aware navigation.",
              "attributes": [
                {
                  "name": "navigate",
                  "type": "string",
                  "required": false,
                  "doc": "Use VerifiedRoutes: `navigate={~p\"/path\"}`"
                },
                {
                  "name": "patch",
                  "type": "string",
                  "required": false,
                  "doc": "Use VerifiedRoutes: `patch={~p\"/path\"}`"
                },
                {
                  "name": "href",
                  "type": "string",
                  "required": false,
                  "doc": "External/legacy target. Prefer `navigate`/`patch` with VerifiedRoutes."
                },
                {
                  "name": "method",
                  "type": "string",
                  "required": false
                },
                {
                  "name": "class",
                  "type": "string",
                  "required": false
                },
                {
                  "name": "replace",
                  "type": "boolean",
                  "required": false
                }
              ],
              "slots": [
                {
                  "name": "inner_block",
                  "required": true,
                  "attributes": []
                }
              ]
            },
            {
              "name": "live_patch",
              "moduleName": "Phoenix.Component",
              "filePath": "/home/dtech/.vscode/extensions/onsever.phoenix-pulse-1.3.0/node_modules/@phoenix-pulse/language-server/resources/phoenix_component_builtins.ex",
              "line": 1,
              "doc": "Phoenix.Component.live_patch/1 – Generates a patch navigation link within the same LiveView.",
              "attributes": [
                {
                  "name": "patch",
                  "type": "string",
                  "required": true,
                  "doc": "Use VerifiedRoutes: `patch={~p\"/path\"}`"
                },
                {
                  "name": "class",
                  "type": "string",
                  "required": false
                },
                {
                  "name": "replace",
                  "type": "boolean",
                  "required": false
                }
              ],
              "slots": [
                {
                  "name": "inner_block",
                  "required": true,
                  "attributes": []
                }
              ]
            },
            {
              "name": "live_redirect",
              "moduleName": "Phoenix.Component",
              "filePath": "/home/dtech/.vscode/extensions/onsever.phoenix-pulse-1.3.0/node_modules/@phoenix-pulse/language-server/resources/phoenix_component_builtins.ex",
              "line": 1,
              "doc": "Phoenix.Component.live_redirect/1 – Generates a redirect navigation link to another LiveView or controller.",
              "attributes": [
                {
                  "name": "navigate",
                  "type": "string",
                  "required": true,
                  "doc": "Use VerifiedRoutes: `navigate={~p\"/path\"}`"
                },
                {
                  "name": "class",
                  "type": "string",
                  "required": false
                },
                {
                  "name": "replace",
                  "type": "boolean",
                  "required": false
                }
              ],
              "slots": [
                {
                  "name": "inner_block",
                  "required": true,
                  "attributes": []
                }
              ]
            },
            {
              "name": "live_component",
              "moduleName": "Phoenix.Component",
              "filePath": "/home/dtech/.vscode/extensions/onsever.phoenix-pulse-1.3.0/node_modules/@phoenix-pulse/language-server/resources/phoenix_component_builtins.ex",
              "line": 1,
              "doc": "Phoenix.Component.live_component/1 – Embeds a stateful LiveComponent from HEEx.",
              "attributes": [
                {
                  "name": "module",
                  "type": "module",
                  "required": true,
                  "doc": "LiveComponent module (e.g., `module={MyAppWeb.ModalComponent}`)."
                },
                {
                  "name": "id",
                  "type": "string",
                  "required": true
                },
                {
                  "name": ":for",
                  "type": "any",
                  "required": false
                },
                {
                  "name": ":let",
                  "type": "any",
                  "required": false
                }
              ],
              "slots": [
                {
                  "name": "inner_block",
                  "required": false,
                  "attributes": []
                }
              ]
            },
            {
              "name": "form",
              "moduleName": "Phoenix.Component",
              "filePath": "/home/dtech/.vscode/extensions/onsever.phoenix-pulse-1.3.0/node_modules/@phoenix-pulse/language-server/resources/phoenix_component_builtins.ex",
              "line": 1,
              "doc": "Phoenix.Component.form/1 – Renders a HEEx form with support for :let assigns and action attributes.",
              "attributes": [
                {
                  "name": "for",
                  "type": "any",
                  "required": true
                },
                {
                  "name": "as",
                  "type": "string",
                  "required": false
                },
                {
                  "name": "id",
                  "type": "string",
                  "required": false
                },
                {
                  "name": "action",
                  "type": "string",
                  "required": false
                },
                {
                  "name": "method",
                  "type": "string",
                  "required": false
                },
                {
                  "name": "phx-submit",
                  "type": "string",
                  "required": false
                },
                {
                  "name": "phx-change",
                  "type": "string",
                  "required": false
                },
                {
                  "name": ":let",
                  "type": "any",
                  "required": false
                }
              ],
              "slots": [
                {
                  "name": "inner_block",
                  "required": true,
                  "attributes": []
                },
                {
                  "name": "actions",
                  "required": false,
                  "attributes": []
                }
              ]
            },
            {
              "name": "inputs_for",
              "moduleName": "Phoenix.Component",
              "filePath": "/home/dtech/.vscode/extensions/onsever.phoenix-pulse-1.3.0/node_modules/@phoenix-pulse/language-server/resources/phoenix_component_builtins.ex",
              "line": 1,
              "doc": "Phoenix.Component.inputs_for/1 – Iterates nested inputs for associations or embeds within a parent form.",
              "attributes": [
                {
                  "name": "field",
                  "type": "any",
                  "required": true,
                  "doc": "Form field or association (e.g., `field={f[:addresses]}`)."
                },
                {
                  "name": ":let",
                  "type": "any",
                  "required": true,
                  "doc": "Binding for the nested form (e.g., `:let={address_form}`)."
                },
                {
                  "name": "for",
                  "type": "any",
                  "required": false,
                  "doc": "Explicit changeset/source for the nested inputs."
                }
              ],
              "slots": [
                {
                  "name": "inner_block",
                  "required": true,
                  "attributes": []
                }
              ]
            }
          ]
        ],
        [
          "/home/dtech/VCF/Blog/zchat/lib/zchat_web/live/UI/feed_live.ex",
          []
        ],
        [
          "/home/dtech/VCF/Blog/zchat/lib/zchat_web/components/core_components.ex",
          [
            {
              "name": "back",
              "moduleName": "ZchatWeb.CoreComponents",
              "filePath": "/home/dtech/VCF/Blog/zchat/lib/zchat_web/components/core_components.ex",
              "line": 566,
              "attributes": [
                {
                  "name": "navigate",
                  "type": "any",
                  "required": true,
                  "rawType": "any"
                }
              ],
              "slots": [
                {
                  "name": "inner_block",
                  "required": true,
                  "attributes": []
                }
              ]
            },
            {
              "name": "list",
              "moduleName": "ZchatWeb.CoreComponents",
              "filePath": "/home/dtech/VCF/Blog/zchat/lib/zchat_web/components/core_components.ex",
              "line": 543,
              "attributes": [],
              "slots": [
                {
                  "name": "item",
                  "required": true,
                  "attributes": [
                    {
                      "default": null,
                      "line": 540,
                      "name": "title",
                      "type": "string",
                      "values": null,
                      "doc": null,
                      "required": true
                    }
                  ]
                }
              ]
            },
            {
              "name": "table",
              "moduleName": "ZchatWeb.CoreComponents",
              "filePath": "/home/dtech/VCF/Blog/zchat/lib/zchat_web/components/core_components.ex",
              "line": 478,
              "attributes": [
                {
                  "name": "row_item",
                  "type": "any",
                  "required": false,
                  "default": "{:&, [line: 469, column: 14], [{:/, [line: 469, column: 32], [{{:., [line: 469, column: 23], [{:__aliases__, [last: [line: 469, column: 15], line: 469, column: 15], [:Function]}, :identity]}, [no_parens: true, line: 469, column: 24], []}, 1]}]}",
                  "doc": "the function for mapping each row before calling the :col and :action slots",
                  "rawType": "any"
                },
                {
                  "name": "row_click",
                  "type": "any",
                  "required": false,
                  "default": "nil",
                  "doc": "the function for handling phx-click on each row",
                  "rawType": "any"
                },
                {
                  "name": "row_id",
                  "type": "any",
                  "required": false,
                  "default": "nil",
                  "doc": "the function for generating the row id",
                  "rawType": "any"
                },
                {
                  "name": "rows",
                  "type": "list",
                  "required": true,
                  "rawType": "list"
                },
                {
                  "name": "id",
                  "type": "string",
                  "required": true,
                  "rawType": "string"
                }
              ],
              "slots": [
                {
                  "name": "action",
                  "required": false,
                  "doc": "the slot for showing user actions in the last table column",
                  "attributes": []
                },
                {
                  "name": "col",
                  "required": true,
                  "attributes": [
                    {
                      "default": null,
                      "line": 473,
                      "name": "label",
                      "type": "string",
                      "values": null,
                      "doc": null,
                      "required": false
                    }
                  ]
                }
              ]
            },
            {
              "name": "header",
              "moduleName": "ZchatWeb.CoreComponents",
              "filePath": "/home/dtech/VCF/Blog/zchat/lib/zchat_web/components/core_components.ex",
              "line": 437,
              "attributes": [
                {
                  "name": "class",
                  "type": "string",
                  "required": false,
                  "default": "nil",
                  "rawType": "string"
                }
              ],
              "slots": [
                {
                  "name": "actions",
                  "required": false,
                  "attributes": []
                },
                {
                  "name": "subtitle",
                  "required": false,
                  "attributes": []
                },
                {
                  "name": "inner_block",
                  "required": true,
                  "attributes": []
                }
              ]
            },
            {
              "name": "error",
              "moduleName": "ZchatWeb.CoreComponents",
              "filePath": "/home/dtech/VCF/Blog/zchat/lib/zchat_web/components/core_components.ex",
              "line": 419,
              "attributes": [],
              "slots": [
                {
                  "name": "inner_block",
                  "required": true,
                  "attributes": []
                }
              ]
            },
            {
              "name": "label",
              "moduleName": "ZchatWeb.CoreComponents",
              "filePath": "/home/dtech/VCF/Blog/zchat/lib/zchat_web/components/core_components.ex",
              "line": 406,
              "attributes": [
                {
                  "name": "for",
                  "type": "string",
                  "required": false,
                  "default": "nil",
                  "rawType": "string"
                }
              ],
              "slots": [
                {
                  "name": "inner_block",
                  "required": true,
                  "attributes": []
                }
              ]
            },
            {
              "name": "input",
              "moduleName": "ZchatWeb.CoreComponents",
              "filePath": "/home/dtech/VCF/Blog/zchat/lib/zchat_web/components/core_components.ex",
              "line": 304,
              "attributes": [
                {
                  "name": "rest",
                  "type": "global",
                  "required": false,
                  "rawType": "global"
                },
                {
                  "name": "multiple",
                  "type": "boolean",
                  "required": false,
                  "default": "false",
                  "doc": "the multiple flag for select inputs",
                  "rawType": "boolean"
                },
                {
                  "name": "options",
                  "type": "list",
                  "required": false,
                  "doc": "the options to pass to Phoenix.HTML.Form.options_for_select/2",
                  "rawType": "list"
                },
                {
                  "name": "prompt",
                  "type": "string",
                  "required": false,
                  "default": "nil",
                  "doc": "the prompt for select inputs",
                  "rawType": "string"
                },
                {
                  "name": "checked",
                  "type": "boolean",
                  "required": false,
                  "doc": "the checked flag for checkbox inputs",
                  "rawType": "boolean"
                },
                {
                  "name": "errors",
                  "type": "list",
                  "required": false,
                  "default": "[]",
                  "rawType": "list"
                },
                {
                  "name": "field",
                  "type": "{:__aliases__, [last: [line: 292, column: 29], line: 292, column: 16], [:Phoenix, :HTML, :FormField]}",
                  "required": false,
                  "doc": "a form field struct retrieved from the form, for example: @form[:email]",
                  "rawType": "{:__aliases__, [last: [line: 292, column: 29], line: 292, column: 16], [:Phoenix, :HTML, :FormField]}"
                },
                {
                  "name": "type",
                  "type": "string",
                  "required": false,
                  "default": "\"text\"",
                  "rawType": "string"
                },
                {
                  "name": "value",
                  "type": "any",
                  "required": false,
                  "rawType": "any"
                },
                {
                  "name": "label",
                  "type": "string",
                  "required": false,
                  "default": "nil",
                  "rawType": "string"
                },
                {
                  "name": "name",
                  "type": "any",
                  "required": false,
                  "rawType": "any"
                },
                {
                  "name": "id",
                  "type": "any",
                  "required": false,
                  "default": "nil",
                  "rawType": "any"
                }
              ],
              "slots": [
                {
                  "name": "inner_block",
                  "required": false,
                  "attributes": []
                }
              ]
            },
            {
              "name": "button",
              "moduleName": "ZchatWeb.CoreComponents",
              "filePath": "/home/dtech/VCF/Blog/zchat/lib/zchat_web/components/core_components.ex",
              "line": 254,
              "attributes": [
                {
                  "name": "rest",
                  "type": "global",
                  "required": false,
                  "rawType": "global"
                },
                {
                  "name": "class",
                  "type": "string",
                  "required": false,
                  "default": "nil",
                  "rawType": "string"
                },
                {
                  "name": "type",
                  "type": "string",
                  "required": false,
                  "default": "nil",
                  "rawType": "string"
                }
              ],
              "slots": [
                {
                  "name": "inner_block",
                  "required": true,
                  "attributes": []
                }
              ]
            },
            {
              "name": "simple_form",
              "moduleName": "ZchatWeb.CoreComponents",
              "filePath": "/home/dtech/VCF/Blog/zchat/lib/zchat_web/components/core_components.ex",
              "line": 227,
              "attributes": [
                {
                  "name": "rest",
                  "type": "global",
                  "required": false,
                  "doc": "the arbitrary HTML attributes to apply to the form tag",
                  "rawType": "global"
                },
                {
                  "name": "as",
                  "type": "any",
                  "required": false,
                  "default": "nil",
                  "doc": "the server side parameter to collect all input under",
                  "rawType": "any"
                },
                {
                  "name": "for",
                  "type": "any",
                  "required": true,
                  "doc": "the datastructure for the form",
                  "rawType": "any"
                }
              ],
              "slots": [
                {
                  "name": "actions",
                  "required": false,
                  "doc": "the slot for form actions, such as a submit button",
                  "attributes": []
                },
                {
                  "name": "inner_block",
                  "required": true,
                  "attributes": []
                }
              ]
            },
            {
              "name": "flash_group",
              "moduleName": "ZchatWeb.CoreComponents",
              "filePath": "/home/dtech/VCF/Blog/zchat/lib/zchat_web/components/core_components.ex",
              "line": 186,
              "attributes": [
                {
                  "name": "flash",
                  "type": "map",
                  "required": true,
                  "doc": "the map of flash messages",
                  "rawType": "map"
                }
              ],
              "slots": []
            },
            {
              "name": "flash",
              "moduleName": "ZchatWeb.CoreComponents",
              "filePath": "/home/dtech/VCF/Blog/zchat/lib/zchat_web/components/core_components.ex",
              "line": 144,
              "attributes": [
                {
                  "name": "rest",
                  "type": "global",
                  "required": false,
                  "doc": "the arbitrary HTML attributes to add to the flash container",
                  "rawType": "global"
                },
                {
                  "name": "close",
                  "type": "boolean",
                  "required": false,
                  "default": "true",
                  "doc": "whether the flash can be closed",
                  "rawType": "boolean"
                },
                {
                  "name": "autoshow",
                  "type": "boolean",
                  "required": false,
                  "default": "true",
                  "doc": "whether to auto show the flash on mount",
                  "rawType": "boolean"
                },
                {
                  "name": "kind",
                  "type": "atom",
                  "required": false,
                  "values": [
                    "info",
                    "error"
                  ],
                  "doc": "used for styling and flash lookup",
                  "rawType": "atom"
                },
                {
                  "name": "title",
                  "type": "string",
                  "required": false,
                  "default": "nil",
                  "rawType": "string"
                },
                {
                  "name": "flash",
                  "type": "map",
                  "required": false,
                  "default": "{:%{}, [closing: [line: 135, column: 33], line: 135, column: 31], []}",
                  "doc": "the map of flash messages to display",
                  "rawType": "map"
                },
                {
                  "name": "id",
                  "type": "string",
                  "required": false,
                  "default": "\"flash\"",
                  "doc": "the optional id of flash container",
                  "rawType": "string"
                }
              ],
              "slots": [
                {
                  "name": "inner_block",
                  "required": false,
                  "doc": "the optional inner block that renders the flash message",
                  "attributes": []
                }
              ]
            },
            {
              "name": "modal",
              "moduleName": "ZchatWeb.CoreComponents",
              "filePath": "/home/dtech/VCF/Blog/zchat/lib/zchat_web/components/core_components.ex",
              "line": 48,
              "attributes": [
                {
                  "name": "on_confirm",
                  "type": "{:__aliases__, [last: [line: 40, column: 21], line: 40, column: 21], [:JS]}",
                  "required": false,
                  "default": "{:%, [line: 40, column: 34], [{:__aliases__, [last: [line: 40, column: 35], line: 40, column: 35], [:JS]}, {:%{}, [closing: [line: 40, column: 38], line: 40, column: 37], []}]}",
                  "rawType": "{:__aliases__, [last: [line: 40, column: 21], line: 40, column: 21], [:JS]}"
                },
                {
                  "name": "on_cancel",
                  "type": "{:__aliases__, [last: [line: 39, column: 20], line: 39, column: 20], [:JS]}",
                  "required": false,
                  "default": "{:%, [line: 39, column: 33], [{:__aliases__, [last: [line: 39, column: 34], line: 39, column: 34], [:JS]}, {:%{}, [closing: [line: 39, column: 37], line: 39, column: 36], []}]}",
                  "rawType": "{:__aliases__, [last: [line: 39, column: 20], line: 39, column: 20], [:JS]}"
                },
                {
                  "name": "show",
                  "type": "boolean",
                  "required": false,
                  "default": "false",
                  "rawType": "boolean"
                },
                {
                  "name": "id",
                  "type": "string",
                  "required": true,
                  "rawType": "string"
                }
              ],
              "slots": [
                {
                  "name": "cancel",
                  "required": false,
                  "attributes": []
                },
                {
                  "name": "confirm",
                  "required": false,
                  "attributes": []
                },
                {
                  "name": "subtitle",
                  "required": false,
                  "attributes": []
                },
                {
                  "name": "title",
                  "required": false,
                  "attributes": []
                },
                {
                  "name": "inner_block",
                  "required": true,
                  "attributes": []
                }
              ]
            }
          ]
        ],
        [
          "/home/dtech/VCF/Blog/zchat/lib/zchat_web/components/layouts.ex",
          []
        ],
        [
          "/home/dtech/VCF/Blog/zchat/lib/zchat_web/controllers/error_html.ex",
          []
        ],
        [
          "/home/dtech/VCF/Blog/zchat/lib/zchat_web/controllers/page_html.ex",
          []
        ]
      ],
      "fileHashes": {
        "/home/dtech/VCF/Blog/zchat/lib/zchat_web/live/UI/feed_live.ex": "8c987cc50c8d9c0f689dfb9b864f0cd42327e98c",
        "/home/dtech/VCF/Blog/zchat/lib/zchat_web/components/core_components.ex": "247a0ab7a08449a48664e5836d6bcdb6e6b172f4",
        "/home/dtech/VCF/Blog/zchat/lib/zchat_web/components/layouts.ex": "631a68c7fa633ca3d7435235968e04ce729f3aa3",
        "/home/dtech/VCF/Blog/zchat/lib/zchat_web/controllers/error_html.ex": "89476411f6169a71df4a964330e48f15ac62e9d9",
        "/home/dtech/VCF/Blog/zchat/lib/zchat_web/controllers/page_html.ex": "d47c6af311aadcccb43e2c040aae74edc23bf1e0"
      },
      "workspaceRoot": "/home/dtech/VCF/Blog"
    },
    "schemas": {
      "schemas": [
        [
          "Zchat.Accounts.User",
          {
            "moduleName": "Zchat.Accounts.User",
            "tableName": "users",
            "fields": [
              {
                "name": "id",
                "type": "id"
              },
              {
                "name": "username",
                "type": "string"
              },
              {
                "name": "email",
                "type": "string"
              },
              {
                "name": "password",
                "type": "string"
              },
              {
                "name": "hashed_password",
                "type": "string"
              },
              {
                "name": "current_password",
                "type": "string"
              },
              {
                "name": "confirmed_at",
                "type": "naive_datetime"
              },
              {
                "name": "posts",
                "type": "list",
                "elixirType": "Zchat.Posts.Post"
              },
              {
                "name": "reposts",
                "type": "list",
                "elixirType": "Zchat.Posts.Repost"
              },
              {
                "name": "likes",
                "type": "list",
                "elixirType": "Zchat.Posts.Like"
              },
              {
                "name": "inserted_at",
                "type": "naive_datetime"
              },
              {
                "name": "updated_at",
                "type": "naive_datetime"
              }
            ],
            "associations": {},
            "associationsDetailed": [],
            "aliases": {},
            "filePath": "/home/dtech/VCF/Blog/zchat/lib/zchat/accounts/user.ex",
            "line": 6
          }
        ],
        [
          "Zchat.Accounts.UserToken",
          {
            "moduleName": "Zchat.Accounts.UserToken",
            "tableName": "users_tokens",
            "fields": [
              {
                "name": "id",
                "type": "id"
              },
              {
                "name": "token",
                "type": "binary"
              },
              {
                "name": "context",
                "type": "string"
              },
              {
                "name": "sent_to",
                "type": "string"
              },
              {
                "name": "user",
                "type": "assoc",
                "elixirType": "Zchat.Accounts.User"
              },
              {
                "name": "inserted_at",
                "type": "naive_datetime"
              },
              {
                "name": "updated_at",
                "type": "naive_datetime"
              }
            ],
            "associations": {},
            "associationsDetailed": [],
            "aliases": {},
            "filePath": "/home/dtech/VCF/Blog/zchat/lib/zchat/accounts/user_token.ex",
            "line": 16
          }
        ],
        [
          "Zchat.Posts.Comment",
          {
            "moduleName": "Zchat.Posts.Comment",
            "tableName": "comments",
            "fields": [
              {
                "name": "id",
                "type": "id"
              },
              {
                "name": "content",
                "type": "string"
              },
              {
                "name": "likes_count",
                "type": "integer"
              },
              {
                "name": "user",
                "type": "assoc",
                "elixirType": "Zchat.Accounts.User"
              },
              {
                "name": "post",
                "type": "assoc",
                "elixirType": "Zchat.Posts.Post"
              },
              {
                "name": "parent",
                "type": "assoc",
                "elixirType": "Zchat.Posts.__MODULE__"
              },
              {
                "name": "replies",
                "type": "list",
                "elixirType": "Zchat.Posts.__MODULE__"
              },
              {
                "name": "likes",
                "type": "list",
                "elixirType": "Zchat.Posts.Like"
              },
              {
                "name": "inserted_at",
                "type": "naive_datetime"
              },
              {
                "name": "updated_at",
                "type": "naive_datetime"
              }
            ],
            "associations": {},
            "associationsDetailed": [],
            "aliases": {},
            "filePath": "/home/dtech/VCF/Blog/zchat/lib/zchat/posts/comment.ex",
            "line": 7
          }
        ],
        [
          "Zchat.Posts.Like",
          {
            "moduleName": "Zchat.Posts.Like",
            "tableName": "likes",
            "fields": [
              {
                "name": "id",
                "type": "id"
              },
              {
                "name": "likeable_type",
                "type": "string"
              },
              {
                "name": "likeable_id",
                "type": "id"
              },
              {
                "name": "user",
                "type": "assoc",
                "elixirType": "Zchat.Accounts.User"
              },
              {
                "name": "inserted_at",
                "type": "naive_datetime"
              },
              {
                "name": "updated_at",
                "type": "naive_datetime"
              }
            ],
            "associations": {},
            "associationsDetailed": [],
            "aliases": {},
            "filePath": "/home/dtech/VCF/Blog/zchat/lib/zchat/posts/like.ex",
            "line": 7
          }
        ],
        [
          "Zchat.Posts.Post",
          {
            "moduleName": "Zchat.Posts.Post",
            "tableName": "posts",
            "fields": [
              {
                "name": "id",
                "type": "id"
              },
              {
                "name": "title",
                "type": "string"
              },
              {
                "name": "content",
                "type": "string"
              },
              {
                "name": "media_url",
                "type": "string"
              },
              {
                "name": "media_type",
                "type": "string"
              },
              {
                "name": "view_count",
                "type": "integer"
              },
              {
                "name": "category",
                "type": "string"
              },
              {
                "name": "reposts_count",
                "type": "integer"
              },
              {
                "name": "likes_count",
                "type": "integer"
              },
              {
                "name": "is_featured",
                "type": "boolean"
              },
              {
                "name": "user",
                "type": "assoc",
                "elixirType": "Zchat.Accounts.User"
              },
              {
                "name": "reposts",
                "type": "list",
                "elixirType": "Zchat.Posts.Repost"
              },
              {
                "name": "comments",
                "type": "list",
                "elixirType": "Zchat.Posts.Comment"
              },
              {
                "name": "likes",
                "type": "list",
                "elixirType": "Zchat.Posts.Like"
              },
              {
                "name": "inserted_at",
                "type": "naive_datetime"
              },
              {
                "name": "updated_at",
                "type": "naive_datetime"
              }
            ],
            "associations": {},
            "associationsDetailed": [],
            "aliases": {},
            "filePath": "/home/dtech/VCF/Blog/zchat/lib/zchat/posts/post.ex",
            "line": 38
          }
        ],
        [
          "Zchat.Posts.Repost",
          {
            "moduleName": "Zchat.Posts.Repost",
            "tableName": "reposts",
            "fields": [
              {
                "name": "id",
                "type": "id"
              },
              {
                "name": "user",
                "type": "assoc",
                "elixirType": "Zchat.Accounts.User"
              },
              {
                "name": "post",
                "type": "assoc",
                "elixirType": "Zchat.Posts.Post"
              },
              {
                "name": "inserted_at",
                "type": "naive_datetime"
              },
              {
                "name": "updated_at",
                "type": "naive_datetime"
              }
            ],
            "associations": {},
            "associationsDetailed": [],
            "aliases": {},
            "filePath": "/home/dtech/VCF/Blog/zchat/lib/zchat/posts/repost.ex",
            "line": 5
          }
        ]
      ],
      "schemasByFile": [
        [
          "/home/dtech/VCF/Blog/zchat/lib/zchat/accounts/user.ex",
          [
            {
              "moduleName": "Zchat.Accounts.User",
              "tableName": "users",
              "fields": [
                {
                  "name": "id",
                  "type": "id"
                },
                {
                  "name": "username",
                  "type": "string"
                },
                {
                  "name": "email",
                  "type": "string"
                },
                {
                  "name": "password",
                  "type": "string"
                },
                {
                  "name": "hashed_password",
                  "type": "string"
                },
                {
                  "name": "current_password",
                  "type": "string"
                },
                {
                  "name": "confirmed_at",
                  "type": "naive_datetime"
                },
                {
                  "name": "posts",
                  "type": "list",
                  "elixirType": "Zchat.Posts.Post"
                },
                {
                  "name": "reposts",
                  "type": "list",
                  "elixirType": "Zchat.Posts.Repost"
                },
                {
                  "name": "likes",
                  "type": "list",
                  "elixirType": "Zchat.Posts.Like"
                },
                {
                  "name": "inserted_at",
                  "type": "naive_datetime"
                },
                {
                  "name": "updated_at",
                  "type": "naive_datetime"
                }
              ],
              "associations": {},
              "associationsDetailed": [],
              "aliases": {},
              "filePath": "/home/dtech/VCF/Blog/zchat/lib/zchat/accounts/user.ex",
              "line": 6
            }
          ]
        ],
        [
          "/home/dtech/VCF/Blog/zchat/lib/zchat/accounts/user_token.ex",
          [
            {
              "moduleName": "Zchat.Accounts.UserToken",
              "tableName": "users_tokens",
              "fields": [
                {
                  "name": "id",
                  "type": "id"
                },
                {
                  "name": "token",
                  "type": "binary"
                },
                {
                  "name": "context",
                  "type": "string"
                },
                {
                  "name": "sent_to",
                  "type": "string"
                },
                {
                  "name": "user",
                  "type": "assoc",
                  "elixirType": "Zchat.Accounts.User"
                },
                {
                  "name": "inserted_at",
                  "type": "naive_datetime"
                },
                {
                  "name": "updated_at",
                  "type": "naive_datetime"
                }
              ],
              "associations": {},
              "associationsDetailed": [],
              "aliases": {},
              "filePath": "/home/dtech/VCF/Blog/zchat/lib/zchat/accounts/user_token.ex",
              "line": 16
            }
          ]
        ],
        [
          "/home/dtech/VCF/Blog/zchat/lib/zchat/posts/comment.ex",
          [
            {
              "moduleName": "Zchat.Posts.Comment",
              "tableName": "comments",
              "fields": [
                {
                  "name": "id",
                  "type": "id"
                },
                {
                  "name": "content",
                  "type": "string"
                },
                {
                  "name": "likes_count",
                  "type": "integer"
                },
                {
                  "name": "user",
                  "type": "assoc",
                  "elixirType": "Zchat.Accounts.User"
                },
                {
                  "name": "post",
                  "type": "assoc",
                  "elixirType": "Zchat.Posts.Post"
                },
                {
                  "name": "parent",
                  "type": "assoc",
                  "elixirType": "Zchat.Posts.__MODULE__"
                },
                {
                  "name": "replies",
                  "type": "list",
                  "elixirType": "Zchat.Posts.__MODULE__"
                },
                {
                  "name": "likes",
                  "type": "list",
                  "elixirType": "Zchat.Posts.Like"
                },
                {
                  "name": "inserted_at",
                  "type": "naive_datetime"
                },
                {
                  "name": "updated_at",
                  "type": "naive_datetime"
                }
              ],
              "associations": {},
              "associationsDetailed": [],
              "aliases": {},
              "filePath": "/home/dtech/VCF/Blog/zchat/lib/zchat/posts/comment.ex",
              "line": 7
            }
          ]
        ],
        [
          "/home/dtech/VCF/Blog/zchat/lib/zchat/posts/like.ex",
          [
            {
              "moduleName": "Zchat.Posts.Like",
              "tableName": "likes",
              "fields": [
                {
                  "name": "id",
                  "type": "id"
                },
                {
                  "name": "likeable_type",
                  "type": "string"
                },
                {
                  "name": "likeable_id",
                  "type": "id"
                },
                {
                  "name": "user",
                  "type": "assoc",
                  "elixirType": "Zchat.Accounts.User"
                },
                {
                  "name": "inserted_at",
                  "type": "naive_datetime"
                },
                {
                  "name": "updated_at",
                  "type": "naive_datetime"
                }
              ],
              "associations": {},
              "associationsDetailed": [],
              "aliases": {},
              "filePath": "/home/dtech/VCF/Blog/zchat/lib/zchat/posts/like.ex",
              "line": 7
            }
          ]
        ],
        [
          "/home/dtech/VCF/Blog/zchat/lib/zchat/posts/post.ex",
          [
            {
              "moduleName": "Zchat.Posts.Post",
              "tableName": "posts",
              "fields": [
                {
                  "name": "id",
                  "type": "id"
                },
                {
                  "name": "title",
                  "type": "string"
                },
                {
                  "name": "content",
                  "type": "string"
                },
                {
                  "name": "media_url",
                  "type": "string"
                },
                {
                  "name": "media_type",
                  "type": "string"
                },
                {
                  "name": "view_count",
                  "type": "integer"
                },
                {
                  "name": "category",
                  "type": "string"
                },
                {
                  "name": "reposts_count",
                  "type": "integer"
                },
                {
                  "name": "likes_count",
                  "type": "integer"
                },
                {
                  "name": "is_featured",
                  "type": "boolean"
                },
                {
                  "name": "user",
                  "type": "assoc",
                  "elixirType": "Zchat.Accounts.User"
                },
                {
                  "name": "reposts",
                  "type": "list",
                  "elixirType": "Zchat.Posts.Repost"
                },
                {
                  "name": "comments",
                  "type": "list",
                  "elixirType": "Zchat.Posts.Comment"
                },
                {
                  "name": "likes",
                  "type": "list",
                  "elixirType": "Zchat.Posts.Like"
                },
                {
                  "name": "inserted_at",
                  "type": "naive_datetime"
                },
                {
                  "name": "updated_at",
                  "type": "naive_datetime"
                }
              ],
              "associations": {},
              "associationsDetailed": [],
              "aliases": {},
              "filePath": "/home/dtech/VCF/Blog/zchat/lib/zchat/posts/post.ex",
              "line": 38
            }
          ]
        ],
        [
          "/home/dtech/VCF/Blog/zchat/lib/zchat/posts/repost.ex",
          [
            {
              "moduleName": "Zchat.Posts.Repost",
              "tableName": "reposts",
              "fields": [
                {
                  "name": "id",
                  "type": "id"
                },
                {
                  "name": "user",
                  "type": "assoc",
                  "elixirType": "Zchat.Accounts.User"
                },
                {
                  "name": "post",
                  "type": "assoc",
                  "elixirType": "Zchat.Posts.Post"
                },
                {
                  "name": "inserted_at",
                  "type": "naive_datetime"
                },
                {
                  "name": "updated_at",
                  "type": "naive_datetime"
                }
              ],
              "associations": {},
              "associationsDetailed": [],
              "aliases": {},
              "filePath": "/home/dtech/VCF/Blog/zchat/lib/zchat/posts/repost.ex",
              "line": 5
            }
          ]
        ]
      ],
      "fileHashes": {
        "/home/dtech/VCF/Blog/zchat/lib/zchat/accounts/user.ex": "83e2e659721d98b4fb64976a26d4203b6f616d0e",
        "/home/dtech/VCF/Blog/zchat/lib/zchat/accounts/user_token.ex": "4286fea45b894747cbb0ea452accc67605179413",
        "/home/dtech/VCF/Blog/zchat/lib/zchat/posts/comment.ex": "959952e29eae810f96482fceb5835380d3e21597",
        "/home/dtech/VCF/Blog/zchat/lib/zchat/posts/like.ex": "cbf4662026130c69f98439d5589bf583e1d1b4b2",
        "/home/dtech/VCF/Blog/zchat/lib/zchat/posts/post.ex": "a7973b70cf5ea69b7663c046e9d6f1280115429a",
        "/home/dtech/VCF/Blog/zchat/lib/zchat/posts/repost.ex": "3ad77af0072eac763d6ee07359ba549ccae500ae"
      },
      "workspaceRoot": "/home/dtech/VCF/Blog"
    },
    "events": {
      "events": [
        [
          "/home/dtech/VCF/Blog/zchat/lib/zchat_web/live/UI/feed_live.ex",
          [
            {
              "name": "post_unliked",
              "filePath": "/home/dtech/VCF/Blog/zchat/lib/zchat_web/live/UI/feed_live.ex",
              "moduleName": "ZchatWeb.UI.FeedLive",
              "line": 128,
              "params": "{post_unliked, %{}}",
              "kind": "handle_info",
              "nameKind": "atom"
            },
            {
              "name": "post_liked",
              "filePath": "/home/dtech/VCF/Blog/zchat/lib/zchat_web/live/UI/feed_live.ex",
              "moduleName": "ZchatWeb.UI.FeedLive",
              "line": 113,
              "params": "{post_liked, like}",
              "kind": "handle_info",
              "nameKind": "atom"
            },
            {
              "name": "new_post",
              "filePath": "/home/dtech/VCF/Blog/zchat/lib/zchat_web/live/UI/feed_live.ex",
              "moduleName": "ZchatWeb.UI.FeedLive",
              "line": 107,
              "params": "{new_post, post}",
              "kind": "handle_info",
              "nameKind": "atom"
            },
            {
              "name": "load_more",
              "filePath": "/home/dtech/VCF/Blog/zchat/lib/zchat_web/live/UI/feed_live.ex",
              "moduleName": "ZchatWeb.UI.FeedLive",
              "line": 101,
              "params": ":atom",
              "kind": "handle_info",
              "nameKind": "atom"
            },
            {
              "name": "toggle_like",
              "filePath": "/home/dtech/VCF/Blog/zchat/lib/zchat_web/live/UI/feed_live.ex",
              "moduleName": "ZchatWeb.UI.FeedLive",
              "line": 95,
              "params": "_params",
              "kind": "handle_event",
              "nameKind": "string"
            },
            {
              "name": "toggle_like",
              "filePath": "/home/dtech/VCF/Blog/zchat/lib/zchat_web/live/UI/feed_live.ex",
              "moduleName": "ZchatWeb.UI.FeedLive",
              "line": 82,
              "params": "%{}",
              "kind": "handle_event",
              "nameKind": "string"
            },
            {
              "name": "load-more",
              "filePath": "/home/dtech/VCF/Blog/zchat/lib/zchat_web/live/UI/feed_live.ex",
              "moduleName": "ZchatWeb.UI.FeedLive",
              "line": 72,
              "params": "_",
              "kind": "handle_event",
              "nameKind": "string"
            }
          ]
        ],
        [
          "/home/dtech/VCF/Blog/zchat/lib/zchat_web/live/user_registration_live.ex",
          [
            {
              "name": "validate",
              "filePath": "/home/dtech/VCF/Blog/zchat/lib/zchat_web/live/user_registration_live.ex",
              "moduleName": "ZchatWeb.UserRegistrationLive",
              "line": 74,
              "params": "%{}",
              "kind": "handle_event",
              "nameKind": "string"
            },
            {
              "name": "save",
              "filePath": "/home/dtech/VCF/Blog/zchat/lib/zchat_web/live/user_registration_live.ex",
              "moduleName": "ZchatWeb.UserRegistrationLive",
              "line": 57,
              "params": "%{}",
              "kind": "handle_event",
              "nameKind": "string"
            }
          ]
        ],
        [
          "/home/dtech/VCF/Blog/zchat/lib/zchat_web/live/user_confirmation_live.ex",
          [
            {
              "name": "confirm_account",
              "filePath": "/home/dtech/VCF/Blog/zchat/lib/zchat_web/live/user_confirmation_live.ex",
              "moduleName": "ZchatWeb.UserConfirmationLive",
              "line": 33,
              "params": "%{}",
              "kind": "handle_event",
              "nameKind": "string"
            }
          ]
        ],
        [
          "/home/dtech/VCF/Blog/zchat/lib/zchat_web/live/user_login_live.ex",
          []
        ],
        [
          "/home/dtech/VCF/Blog/zchat/lib/zchat_web/live/home_live.ex",
          []
        ],
        [
          "/home/dtech/VCF/Blog/zchat/lib/zchat_web/live/create_post_live.ex",
          [
            {
              "name": "validate",
              "filePath": "/home/dtech/VCF/Blog/zchat/lib/zchat_web/live/create_post_live.ex",
              "moduleName": "ZchatWeb.CreatePost",
              "line": 29,
              "params": "%{\"post\" => post_params}",
              "kind": "handle_event",
              "clause": "def handle_event(\"validate\", %{\"post\" => post_params}, socket) do",
              "nameKind": "string"
            },
            {
              "name": "add_tag",
              "filePath": "/home/dtech/VCF/Blog/zchat/lib/zchat_web/live/create_post_live.ex",
              "moduleName": "ZchatWeb.CreatePost",
              "line": 44,
              "params": "%{\"tag\" => tag}",
              "kind": "handle_event",
              "clause": "def handle_event(\"add_tag\", %{\"tag\" => tag}, socket) do",
              "nameKind": "string"
            },
            {
              "name": "remove_tag",
              "filePath": "/home/dtech/VCF/Blog/zchat/lib/zchat_web/live/create_post_live.ex",
              "moduleName": "ZchatWeb.CreatePost",
              "line": 60,
              "params": "%{\"tag\" => tag}",
              "kind": "handle_event",
              "clause": "def handle_event(\"remove_tag\", %{\"tag\" => tag}, socket) do",
              "nameKind": "string"
            },
            {
              "name": "save",
              "filePath": "/home/dtech/VCF/Blog/zchat/lib/zchat_web/live/create_post_live.ex",
              "moduleName": "ZchatWeb.CreatePost",
              "line": 70,
              "params": "%{\"post\" => post_params}",
              "kind": "handle_event",
              "clause": "def handle_event(\"save\", %{\"post\" => post_params}, socket) do",
              "nameKind": "string"
            },
            {
              "name": "cancel-upload",
              "filePath": "/home/dtech/VCF/Blog/zchat/lib/zchat_web/live/create_post_live.ex",
              "moduleName": "ZchatWeb.CreatePost",
              "line": 115,
              "params": "%{\"ref\" => ref}",
              "kind": "handle_event",
              "clause": "def handle_event(\"cancel-upload\", %{\"ref\" => ref}, socket) do",
              "nameKind": "string"
            }
          ]
        ],
        [
          "/home/dtech/VCF/Blog/zchat/lib/zchat_web/live/UI/single_post_live.ex",
          [
            {
              "name": "validate",
              "filePath": "/home/dtech/VCF/Blog/zchat/lib/zchat_web/live/UI/single_post_live.ex",
              "moduleName": "ZchatWeb.UI.SinglePostLive",
              "line": 47,
              "params": "%{\"comment\" => params}",
              "kind": "handle_event",
              "clause": "def handle_event(\"validate\", %{\"comment\" => params}, socket) do",
              "nameKind": "string"
            },
            {
              "name": "add_comment",
              "filePath": "/home/dtech/VCF/Blog/zchat/lib/zchat_web/live/UI/single_post_live.ex",
              "moduleName": "ZchatWeb.UI.SinglePostLive",
              "line": 57,
              "params": "%{\"comment\" => comment_params}",
              "kind": "handle_event",
              "clause": "def handle_event(\"add_comment\", %{\"comment\" => comment_params}, socket) do",
              "nameKind": "string"
            },
            {
              "name": "reply_to",
              "filePath": "/home/dtech/VCF/Blog/zchat/lib/zchat_web/live/UI/single_post_live.ex",
              "moduleName": "ZchatWeb.UI.SinglePostLive",
              "line": 81,
              "params": "%{\"parent_id\" => parent_id}",
              "kind": "handle_event",
              "clause": "def handle_event(\"reply_to\", %{\"parent_id\" => parent_id}, socket) do",
              "nameKind": "string"
            },
            {
              "name": "cancel_reply",
              "filePath": "/home/dtech/VCF/Blog/zchat/lib/zchat_web/live/UI/single_post_live.ex",
              "moduleName": "ZchatWeb.UI.SinglePostLive",
              "line": 87,
              "params": "_",
              "kind": "handle_event",
              "clause": "def handle_event(\"cancel_reply\", _, socket) do",
              "nameKind": "string"
            },
            {
              "name": "like_comment",
              "filePath": "/home/dtech/VCF/Blog/zchat/lib/zchat_web/live/UI/single_post_live.ex",
              "moduleName": "ZchatWeb.UI.SinglePostLive",
              "line": 93,
              "params": "%{\"comment_id\" => _id}",
              "kind": "handle_event",
              "clause": "def handle_event(\"like_comment\", %{\"comment_id\" => _id}, socket) do",
              "nameKind": "string"
            },
            {
              "name": "toggle_like",
              "filePath": "/home/dtech/VCF/Blog/zchat/lib/zchat_web/live/UI/single_post_live.ex",
              "moduleName": "ZchatWeb.UI.SinglePostLive",
              "line": 99,
              "params": "_params",
              "kind": "handle_event",
              "clause": "def handle_event(\"toggle_like\", _params, socket) do",
              "nameKind": "string"
            }
          ]
        ],
        [
          "/home/dtech/VCF/Blog/zchat/lib/zchat_web/live/post_show_live.ex",
          []
        ],
        [
          "/home/dtech/VCF/Blog/zchat/lib/zchat_web/live/user_forgot_password_live.ex",
          [
            {
              "name": "send_email",
              "filePath": "/home/dtech/VCF/Blog/zchat/lib/zchat_web/live/user_forgot_password_live.ex",
              "moduleName": "ZchatWeb.UserForgotPasswordLive",
              "line": 34,
              "params": "%{\"user\" => %{\"email\" => email}}",
              "kind": "handle_event",
              "clause": "def handle_event(\"send_email\", %{\"user\" => %{\"email\" => email}}, socket) do",
              "nameKind": "string"
            }
          ]
        ],
        [
          "/home/dtech/VCF/Blog/zchat/lib/zchat_web/live/user_confirmation_instructions_live.ex",
          [
            {
              "name": "send_instructions",
              "filePath": "/home/dtech/VCF/Blog/zchat/lib/zchat_web/live/user_confirmation_instructions_live.ex",
              "moduleName": "ZchatWeb.UserConfirmationInstructionsLive",
              "line": 35,
              "params": "%{\"user\" => %{\"email\" => email}}",
              "kind": "handle_event",
              "clause": "def handle_event(\"send_instructions\", %{\"user\" => %{\"email\" => email}}, socket) do",
              "nameKind": "string"
            }
          ]
        ],
        [
          "/home/dtech/VCF/Blog/zchat/lib/zchat_web/live/user_reset_password_live.ex",
          [
            {
              "name": "reset_password",
              "filePath": "/home/dtech/VCF/Blog/zchat/lib/zchat_web/live/user_reset_password_live.ex",
              "moduleName": "ZchatWeb.UserResetPasswordLive",
              "line": 58,
              "params": "%{\"user\" => user_params}",
              "kind": "handle_event",
              "clause": "def handle_event(\"reset_password\", %{\"user\" => user_params}, socket) do",
              "nameKind": "string"
            },
            {
              "name": "validate",
              "filePath": "/home/dtech/VCF/Blog/zchat/lib/zchat_web/live/user_reset_password_live.ex",
              "moduleName": "ZchatWeb.UserResetPasswordLive",
              "line": 71,
              "params": "%{\"user\" => user_params}",
              "kind": "handle_event",
              "clause": "def handle_event(\"validate\", %{\"user\" => user_params}, socket) do",
              "nameKind": "string"
            }
          ]
        ],
        [
          "/home/dtech/VCF/Blog/zchat/lib/zchat_web/live/user_settings_live.ex",
          [
            {
              "name": "validate_email",
              "filePath": "/home/dtech/VCF/Blog/zchat/lib/zchat_web/live/user_settings_live.ex",
              "moduleName": "ZchatWeb.UserSettingsLive",
              "line": 106,
              "params": "params",
              "kind": "handle_event",
              "clause": "def handle_event(\"validate_email\", params, socket) do",
              "nameKind": "string"
            },
            {
              "name": "update_email",
              "filePath": "/home/dtech/VCF/Blog/zchat/lib/zchat_web/live/user_settings_live.ex",
              "moduleName": "ZchatWeb.UserSettingsLive",
              "line": 118,
              "params": "params",
              "kind": "handle_event",
              "clause": "def handle_event(\"update_email\", params, socket) do",
              "nameKind": "string"
            },
            {
              "name": "validate_password",
              "filePath": "/home/dtech/VCF/Blog/zchat/lib/zchat_web/live/user_settings_live.ex",
              "moduleName": "ZchatWeb.UserSettingsLive",
              "line": 138,
              "params": "params",
              "kind": "handle_event",
              "clause": "def handle_event(\"validate_password\", params, socket) do",
              "nameKind": "string"
            },
            {
              "name": "update_password",
              "filePath": "/home/dtech/VCF/Blog/zchat/lib/zchat_web/live/user_settings_live.ex",
              "moduleName": "ZchatWeb.UserSettingsLive",
              "line": 150,
              "params": "params",
              "kind": "handle_event",
              "clause": "def handle_event(\"update_password\", params, socket) do",
              "nameKind": "string"
            }
          ]
        ]
      ],
      "fileHashes": {
        "/home/dtech/VCF/Blog/zchat/lib/zchat_web/live/UI/feed_live.ex": "8c987cc50c8d9c0f689dfb9b864f0cd42327e98c",
        "/home/dtech/VCF/Blog/zchat/lib/zchat_web/live/user_registration_live.ex": "f583f717ddffe2fdfc36c4cbbd443b959f24457e",
        "/home/dtech/VCF/Blog/zchat/lib/zchat_web/live/user_confirmation_live.ex": "038c0a4684bfa3e4d3c99170cd8c8f943ea88f00",
        "/home/dtech/VCF/Blog/zchat/lib/zchat_web/live/user_login_live.ex": "dfbc89fa7922ccc22ae6405efb602e8fdf0569a0",
        "/home/dtech/VCF/Blog/zchat/lib/zchat_web/live/home_live.ex": "7a8fa433e1e4434577f1f3f3c202c7a75072f400",
        "/home/dtech/VCF/Blog/zchat/lib/zchat_web/live/create_post_live.ex": "f0e639fac4d959fd03ea488fc9949c5e30464dfc",
        "/home/dtech/VCF/Blog/zchat/lib/zchat_web/live/UI/single_post_live.ex": "7d90654f53d3447fb3730430606f82603a529cf4",
        "/home/dtech/VCF/Blog/zchat/lib/zchat_web/live/post_show_live.ex": "8b9d4f266178f86da3fdc911d18e597836263472",
        "/home/dtech/VCF/Blog/zchat/lib/zchat_web/live/user_forgot_password_live.ex": "4b1bcc061ae9e06a7521d3eafba8d9bc0247c57b",
        "/home/dtech/VCF/Blog/zchat/lib/zchat_web/live/user_confirmation_instructions_live.ex": "bc43d0aa10e3c7ca70bf2c16fe31bf7ab6d09ea6",
        "/home/dtech/VCF/Blog/zchat/lib/zchat_web/live/user_reset_password_live.ex": "962c5971bc4c3017fe1c87e4c98248931c2b30e6",
        "/home/dtech/VCF/Blog/zchat/lib/zchat_web/live/user_settings_live.ex": "06e4d05117aa607cb2c9549010640a44ddb68868"
      },
      "workspaceRoot": "/home/dtech/VCF/Blog"
    },
    "routes": {
      "routes": [
        {
          "verb": "LIVE",
          "path": "/",
          "filePath": "/home/dtech/VCF/Blog/zchat/lib/zchat_web/router.ex",
          "line": 24,
          "liveModule": "HomeLive",
          "helperBase": "root",
          "params": [],
          "isResource": false,
          "pipeline": "browser"
        },
        {
          "verb": "LIVE",
          "path": "/posts/new",
          "filePath": "/home/dtech/VCF/Blog/zchat/lib/zchat_web/router.ex",
          "line": 25,
          "liveModule": "CreatePost",
          "helperBase": "post_new",
          "params": [],
          "isResource": false,
          "pipeline": "browser"
        },
        {
          "verb": "FORWARD",
          "path": "/dev/mailbox",
          "filePath": "/home/dtech/VCF/Blog/zchat/lib/zchat_web/router.ex",
          "line": 47,
          "forwardTo": "Plug.Swoosh.MailboxPreview",
          "helperBase": "mailbox",
          "params": [],
          "isResource": false,
          "pipeline": "browser",
          "scopePath": "/dev"
        },
        {
          "verb": "LIVE",
          "path": "/users/register",
          "filePath": "/home/dtech/VCF/Blog/zchat/lib/zchat_web/router.ex",
          "line": 58,
          "liveModule": "UserRegistrationLive",
          "helperBase": "user_register",
          "params": [],
          "isResource": false
        },
        {
          "verb": "LIVE",
          "path": "/users/log_in",
          "filePath": "/home/dtech/VCF/Blog/zchat/lib/zchat_web/router.ex",
          "line": 59,
          "liveModule": "UserLoginLive",
          "helperBase": "user_log_in",
          "params": [],
          "isResource": false
        },
        {
          "verb": "LIVE",
          "path": "/users/reset_password",
          "filePath": "/home/dtech/VCF/Blog/zchat/lib/zchat_web/router.ex",
          "line": 60,
          "liveModule": "UserForgotPasswordLive",
          "helperBase": "user_reset_password",
          "params": [],
          "isResource": false
        },
        {
          "verb": "LIVE",
          "path": "/users/reset_password/:token",
          "filePath": "/home/dtech/VCF/Blog/zchat/lib/zchat_web/router.ex",
          "line": 61,
          "liveModule": "UserResetPasswordLive",
          "helperBase": "user_reset_password",
          "params": [
            "token"
          ],
          "isResource": false
        },
        {
          "verb": "POST",
          "path": "/users/log_in",
          "filePath": "/home/dtech/VCF/Blog/zchat/lib/zchat_web/router.ex",
          "line": 65,
          "controller": "UserSessionController",
          "action": "create",
          "helperBase": "user_log_in",
          "params": [],
          "isResource": false
        },
        {
          "verb": "LIVE",
          "path": "/feed",
          "filePath": "/home/dtech/VCF/Blog/zchat/lib/zchat_web/router.ex",
          "line": 74,
          "liveModule": "UI.FeedLive",
          "liveAction": "FeedLive",
          "helperBase": "feed",
          "params": [],
          "isResource": false
        },
        {
          "verb": "LIVE",
          "path": "/users/settings",
          "filePath": "/home/dtech/VCF/Blog/zchat/lib/zchat_web/router.ex",
          "line": 75,
          "liveModule": "UserSettingsLive",
          "helperBase": "user_setting",
          "params": [],
          "isResource": false
        },
        {
          "verb": "LIVE",
          "path": "/users/settings/confirm_email/:token",
          "filePath": "/home/dtech/VCF/Blog/zchat/lib/zchat_web/router.ex",
          "line": 76,
          "liveModule": "UserSettingsLive",
          "helperBase": "user_setting_confirm_email",
          "params": [
            "token"
          ],
          "isResource": false
        },
        {
          "verb": "LIVE",
          "path": "/posts/:id",
          "filePath": "/home/dtech/VCF/Blog/zchat/lib/zchat_web/router.ex",
          "line": 77,
          "liveModule": "UI.SinglePostLive",
          "liveAction": "SinglePostLive",
          "helperBase": "post",
          "params": [
            "id"
          ],
          "isResource": false
        },
        {
          "verb": "DELETE",
          "path": "/users/log_out",
          "filePath": "/home/dtech/VCF/Blog/zchat/lib/zchat_web/router.ex",
          "line": 84,
          "controller": "UserSessionController",
          "action": "delete",
          "helperBase": "user_log_out",
          "params": [],
          "isResource": false
        },
        {
          "verb": "LIVE",
          "path": "/users/confirm/:token",
          "filePath": "/home/dtech/VCF/Blog/zchat/lib/zchat_web/router.ex",
          "line": 88,
          "liveModule": "UserConfirmationLive",
          "helperBase": "user_confirm",
          "params": [
            "token"
          ],
          "isResource": false
        },
        {
          "verb": "LIVE",
          "path": "/users/confirm",
          "filePath": "/home/dtech/VCF/Blog/zchat/lib/zchat_web/router.ex",
          "line": 89,
          "liveModule": "UserConfirmationInstructionsLive",
          "helperBase": "user_confirm",
          "params": [],
          "isResource": false
        }
      ],
      "fileHashes": {
        "/home/dtech/VCF/Blog/zchat/lib/zchat_web/router.ex": "a589dd52f9f8d4c1b9721a39bafe1dced32980b6"
      },
      "workspaceRoot": "/home/dtech/VCF/Blog"
    },
    "controllers": {
      "rendersByFile": [
        [
          "/home/dtech/VCF/Blog/zchat/lib/zchat_web/controllers/page_controller.ex",
          [
            {
              "controllerModule": "ZchatWeb.PageController",
              "controllerFile": "/home/dtech/VCF/Blog/zchat/lib/zchat_web/controllers/page_controller.ex",
              "action": "home",
              "templateName": "home",
              "assigns": [
                "layout"
              ],
              "assignsWithTypes": [
                {
                  "name": "layout",
                  "variableName": "false",
                  "typeInfo": {
                    "kind": "boolean"
                  }
                }
              ],
              "actionBody": "  def home(conn, _params) do\n    # The home page is often custom made,\n    # so skip the default app layout.\n    render(conn, :home, layout: false)\n  end",
              "line": 7,
              "templatePath": "/home/dtech/VCF/Blog/zchat/lib/zchat_web/controllers/page_html/home.html.heex"
            }
          ]
        ],
        [
          "/home/dtech/VCF/Blog/zchat/lib/zchat_web/controllers/user_session_controller.ex",
          []
        ]
      ],
      "templateSummaries": [
        [
          "/home/dtech/VCF/Blog/zchat/lib/zchat_web/controllers/page_html/home.html.heex",
          {
            "templatePath": "/home/dtech/VCF/Blog/zchat/lib/zchat_web/controllers/page_html/home.html.heex",
            "assignSources": {},
            "controllers": [
              {
                "controllerModule": "ZchatWeb.PageController",
                "controllerFile": "/home/dtech/VCF/Blog/zchat/lib/zchat_web/controllers/page_controller.ex",
                "action": "home",
                "templateName": "home",
                "assigns": [
                  "layout"
                ],
                "assignsWithTypes": [
                  {
                    "name": "layout",
                    "variableName": "false",
                    "typeInfo": {
                      "kind": "boolean"
                    }
                  }
                ],
                "actionBody": "  def home(conn, _params) do\n    # The home page is often custom made,\n    # so skip the default app layout.\n    render(conn, :home, layout: false)\n  end",
                "line": 7,
                "templatePath": "/home/dtech/VCF/Blog/zchat/lib/zchat_web/controllers/page_html/home.html.heex"
              }
            ]
          }
        ]
      ],
      "fileHashes": {
        "/home/dtech/VCF/Blog/zchat/lib/zchat_web/controllers/page_controller.ex": "3904b2e13715bcdf411bdc87d241ec1284ec6fb4",
        "/home/dtech/VCF/Blog/zchat/lib/zchat_web/controllers/user_session_controller.ex": "10331551dc4eb0735666646e4642a2647f82cde9"
      },
      "workspaceRoot": "/home/dtech/VCF/Blog"
    },
    "templates": {
      "templatesByModule": [
        [
          "ZchatWeb.PageHTML",
          [
            {
              "moduleName": "ZchatWeb.PageHTML",
              "name": "home",
              "format": "html",
              "filePath": "/home/dtech/VCF/Blog/zchat/lib/zchat_web/controllers/page_html/home.html.heex"
            }
          ]
        ],
        [
          "ZchatWeb.UI.PostComponent",
          [
            {
              "moduleName": "ZchatWeb.UI.PostComponent",
              "name": "update",
              "format": "html",
              "filePath": "/home/dtech/VCF/Blog/zchat/lib/zchat_web/live/UI/post_component.ex#update"
            }
          ]
        ],
        [
          "ZchatWeb.UserConfirmationInstructionsLive",
          [
            {
              "moduleName": "ZchatWeb.UserConfirmationInstructionsLive",
              "name": "render",
              "format": "html",
              "filePath": "/home/dtech/VCF/Blog/zchat/lib/zchat_web/live/user_confirmation_instructions_live.ex#render"
            }
          ]
        ],
        [
          "ZchatWeb.PostShowLive",
          [
            {
              "moduleName": "ZchatWeb.PostShowLive",
              "name": "render",
              "format": "html",
              "filePath": "/home/dtech/VCF/Blog/zchat/lib/zchat_web/live/post_show_live.ex#render"
            }
          ]
        ],
        [
          "ZchatWeb.UserLoginLive",
          [
            {
              "moduleName": "ZchatWeb.UserLoginLive",
              "name": "render",
              "format": "html",
              "filePath": "/home/dtech/VCF/Blog/zchat/lib/zchat_web/live/user_login_live.ex#render"
            }
          ]
        ],
        [
          "ZchatWeb.UserForgotPasswordLive",
          [
            {
              "moduleName": "ZchatWeb.UserForgotPasswordLive",
              "name": "render",
              "format": "html",
              "filePath": "/home/dtech/VCF/Blog/zchat/lib/zchat_web/live/user_forgot_password_live.ex#render"
            }
          ]
        ],
        [
          "ZchatWeb.UserRegistrationLive",
          [
            {
              "moduleName": "ZchatWeb.UserRegistrationLive",
              "name": "render",
              "format": "html",
              "filePath": "/home/dtech/VCF/Blog/zchat/lib/zchat_web/live/user_registration_live.ex#render"
            }
          ]
        ],
        [
          "ZchatWeb.UserSettingsLive",
          [
            {
              "moduleName": "ZchatWeb.UserSettingsLive",
              "name": "render",
              "format": "html",
              "filePath": "/home/dtech/VCF/Blog/zchat/lib/zchat_web/live/user_settings_live.ex#render"
            }
          ]
        ],
        [
          "ZchatWeb.UserResetPasswordLive",
          [
            {
              "moduleName": "ZchatWeb.UserResetPasswordLive",
              "name": "render",
              "format": "html",
              "filePath": "/home/dtech/VCF/Blog/zchat/lib/zchat_web/live/user_reset_password_live.ex#render"
            }
          ]
        ]
      ],
      "templatesByPath": [
        [
          "/home/dtech/VCF/Blog/zchat/lib/zchat_web/controllers/page_html/home.html.heex",
          {
            "moduleName": "ZchatWeb.PageHTML",
            "name": "home",
            "format": "html",
            "filePath": "/home/dtech/VCF/Blog/zchat/lib/zchat_web/controllers/page_html/home.html.heex"
          }
        ],
        [
          "/home/dtech/VCF/Blog/zchat/lib/zchat_web/live/UI/post_component.ex#update",
          {
            "moduleName": "ZchatWeb.UI.PostComponent",
            "name": "update",
            "format": "html",
            "filePath": "/home/dtech/VCF/Blog/zchat/lib/zchat_web/live/UI/post_component.ex#update"
          }
        ],
        [
          "/home/dtech/VCF/Blog/zchat/lib/zchat_web/live/user_confirmation_instructions_live.ex#render",
          {
            "moduleName": "ZchatWeb.UserConfirmationInstructionsLive",
            "name": "render",
            "format": "html",
            "filePath": "/home/dtech/VCF/Blog/zchat/lib/zchat_web/live/user_confirmation_instructions_live.ex#render"
          }
        ],
        [
          "/home/dtech/VCF/Blog/zchat/lib/zchat_web/live/post_show_live.ex#render",
          {
            "moduleName": "ZchatWeb.PostShowLive",
            "name": "render",
            "format": "html",
            "filePath": "/home/dtech/VCF/Blog/zchat/lib/zchat_web/live/post_show_live.ex#render"
          }
        ],
        [
          "/home/dtech/VCF/Blog/zchat/lib/zchat_web/live/user_login_live.ex#render",
          {
            "moduleName": "ZchatWeb.UserLoginLive",
            "name": "render",
            "format": "html",
            "filePath": "/home/dtech/VCF/Blog/zchat/lib/zchat_web/live/user_login_live.ex#render"
          }
        ],
        [
          "/home/dtech/VCF/Blog/zchat/lib/zchat_web/live/user_forgot_password_live.ex#render",
          {
            "moduleName": "ZchatWeb.UserForgotPasswordLive",
            "name": "render",
            "format": "html",
            "filePath": "/home/dtech/VCF/Blog/zchat/lib/zchat_web/live/user_forgot_password_live.ex#render"
          }
        ],
        [
          "/home/dtech/VCF/Blog/zchat/lib/zchat_web/live/user_registration_live.ex#render",
          {
            "moduleName": "ZchatWeb.UserRegistrationLive",
            "name": "render",
            "format": "html",
            "filePath": "/home/dtech/VCF/Blog/zchat/lib/zchat_web/live/user_registration_live.ex#render"
          }
        ],
        [
          "/home/dtech/VCF/Blog/zchat/lib/zchat_web/live/user_settings_live.ex#render",
          {
            "moduleName": "ZchatWeb.UserSettingsLive",
            "name": "render",
            "format": "html",
            "filePath": "/home/dtech/VCF/Blog/zchat/lib/zchat_web/live/user_settings_live.ex#render"
          }
        ],
        [
          "/home/dtech/VCF/Blog/zchat/lib/zchat_web/live/user_reset_password_live.ex#render",
          {
            "moduleName": "ZchatWeb.UserResetPasswordLive",
            "name": "render",
            "format": "html",
            "filePath": "/home/dtech/VCF/Blog/zchat/lib/zchat_web/live/user_reset_password_live.ex#render"
          }
        ]
      ],
      "moduleByFile": [
        [
          "/home/dtech/VCF/Blog/zchat/lib/zchat_web/controllers/page_html.ex",
          "ZchatWeb.PageHTML"
        ],
        [
          "/home/dtech/VCF/Blog/zchat/lib/zchat_web/live/UI/post_component.ex",
          "ZchatWeb.UI.PostComponent"
        ],
        [
          "/home/dtech/VCF/Blog/zchat/lib/zchat_web/live/user_confirmation_instructions_live.ex",
          "ZchatWeb.UserConfirmationInstructionsLive"
        ],
        [
          "/home/dtech/VCF/Blog/zchat/lib/zchat_web/live/post_show_live.ex",
          "ZchatWeb.PostShowLive"
        ],
        [
          "/home/dtech/VCF/Blog/zchat/lib/zchat_web/live/user_login_live.ex",
          "ZchatWeb.UserLoginLive"
        ],
        [
          "/home/dtech/VCF/Blog/zchat/lib/zchat_web/live/user_forgot_password_live.ex",
          "ZchatWeb.UserForgotPasswordLive"
        ],
        [
          "/home/dtech/VCF/Blog/zchat/lib/zchat_web/live/user_registration_live.ex",
          "ZchatWeb.UserRegistrationLive"
        ],
        [
          "/home/dtech/VCF/Blog/zchat/lib/zchat_web/live/user_settings_live.ex",
          "ZchatWeb.UserSettingsLive"
        ],
        [
          "/home/dtech/VCF/Blog/zchat/lib/zchat_web/live/user_reset_password_live.ex",
          "ZchatWeb.UserResetPasswordLive"
        ]
      ],
      "fileHashes": {
        "/home/dtech/VCF/Blog/zchat/lib/zchat_web/controllers/page_html.ex": "d47c6af311aadcccb43e2c040aae74edc23bf1e0",
        "/home/dtech/VCF/Blog/zchat/lib/zchat_web/live/UI/post_component.ex": "aa6a226a47f2649ce4a085faf975b962d7a906b1",
        "/home/dtech/VCF/Blog/zchat/lib/zchat_web/live/user_confirmation_instructions_live.ex": "bc43d0aa10e3c7ca70bf2c16fe31bf7ab6d09ea6",
        "/home/dtech/VCF/Blog/zchat/lib/zchat_web/live/post_show_live.ex": "8b9d4f266178f86da3fdc911d18e597836263472",
        "/home/dtech/VCF/Blog/zchat/lib/zchat_web/live/user_login_live.ex": "dfbc89fa7922ccc22ae6405efb602e8fdf0569a0",
        "/home/dtech/VCF/Blog/zchat/lib/zchat_web/live/user_forgot_password_live.ex": "4b1bcc061ae9e06a7521d3eafba8d9bc0247c57b",
        "/home/dtech/VCF/Blog/zchat/lib/zchat_web/live/user_registration_live.ex": "f583f717ddffe2fdfc36c4cbbd443b959f24457e",
        "/home/dtech/VCF/Blog/zchat/lib/zchat_web/live/user_settings_live.ex": "06e4d05117aa607cb2c9549010640a44ddb68868",
        "/home/dtech/VCF/Blog/zchat/lib/zchat_web/live/user_reset_password_live.ex": "962c5971bc4c3017fe1c87e4c98248931c2b30e6"
      },
      "workspaceRoot": "/home/dtech/VCF/Blog"
    },
    "liveview": {
      "liveViews": [
        [
          "/home/dtech/VCF/Blog/zchat/lib/zchat_web/live/UI/feed_live.ex",
          {
            "module": "ZchatWeb.UI.FeedLive",
            "filePath": "/home/dtech/VCF/Blog/zchat/lib/zchat_web/live/UI/feed_live.ex",
            "functions": [
              {
                "line": 128,
                "name": "post_unliked",
                "type": "handle_info",
                "module_name": "ZchatWeb.UI.FeedLive",
                "event_name": "post_unliked"
              },
              {
                "line": 113,
                "name": "post_liked",
                "type": "handle_info",
                "module_name": "ZchatWeb.UI.FeedLive",
                "event_name": "post_liked"
              },
              {
                "line": 107,
                "name": "new_post",
                "type": "handle_info",
                "module_name": "ZchatWeb.UI.FeedLive",
                "event_name": "new_post"
              },
              {
                "line": 101,
                "name": "load_more",
                "type": "handle_info",
                "module_name": "ZchatWeb.UI.FeedLive",
                "event_name": "load_more"
              },
              {
                "line": 95,
                "name": "toggle_like",
                "type": "handle_event",
                "module_name": "ZchatWeb.UI.FeedLive",
                "event_name": "toggle_like"
              },
              {
                "line": 82,
                "name": "toggle_like",
                "type": "handle_event",
                "module_name": "ZchatWeb.UI.FeedLive",
                "event_name": "toggle_like"
              },
              {
                "line": 72,
                "name": "load-more",
                "type": "handle_event",
                "module_name": "ZchatWeb.UI.FeedLive",
                "event_name": "load-more"
              },
              {
                "line": 30,
                "name": "handle_params",
                "type": "handle_params",
                "module_name": "ZchatWeb.UI.FeedLive"
              },
              {
                "line": 8,
                "name": "mount",
                "type": "mount",
                "module_name": "ZchatWeb.UI.FeedLive"
              }
            ]
          }
        ],
        [
          "/home/dtech/VCF/Blog/zchat/lib/zchat_web/live/post_show_live.ex",
          {
            "module": "ZchatWeb.PostShowLive",
            "filePath": "/home/dtech/VCF/Blog/zchat/lib/zchat_web/live/post_show_live.ex",
            "functions": [
              {
                "line": 12,
                "name": "render",
                "type": "render",
                "module_name": "ZchatWeb.PostShowLive"
              },
              {
                "line": 7,
                "name": "mount",
                "type": "mount",
                "module_name": "ZchatWeb.PostShowLive"
              }
            ]
          }
        ],
        [
          "/home/dtech/VCF/Blog/zchat/lib/zchat_web/live/user_login_live.ex",
          {
            "module": "ZchatWeb.UserLoginLive",
            "filePath": "/home/dtech/VCF/Blog/zchat/lib/zchat_web/live/user_login_live.ex",
            "functions": [
              {
                "line": 38,
                "name": "mount",
                "type": "mount",
                "module_name": "ZchatWeb.UserLoginLive"
              },
              {
                "line": 4,
                "name": "render",
                "type": "render",
                "module_name": "ZchatWeb.UserLoginLive"
              }
            ]
          }
        ],
        [
          "/home/dtech/VCF/Blog/zchat/lib/zchat_web/live/user_registration_live.ex",
          {
            "module": "ZchatWeb.UserRegistrationLive",
            "filePath": "/home/dtech/VCF/Blog/zchat/lib/zchat_web/live/user_registration_live.ex",
            "functions": [
              {
                "line": 74,
                "name": "validate",
                "type": "handle_event",
                "module_name": "ZchatWeb.UserRegistrationLive",
                "event_name": "validate"
              },
              {
                "line": 57,
                "name": "save",
                "type": "handle_event",
                "module_name": "ZchatWeb.UserRegistrationLive",
                "event_name": "save"
              },
              {
                "line": 46,
                "name": "mount",
                "type": "mount",
                "module_name": "ZchatWeb.UserRegistrationLive"
              },
              {
                "line": 7,
                "name": "render",
                "type": "render",
                "module_name": "ZchatWeb.UserRegistrationLive"
              }
            ]
          }
        ],
        [
          "/home/dtech/VCF/Blog/zchat/lib/zchat_web/live/user_settings_live.ex",
          {
            "module": "ZchatWeb.UserSettingsLive",
            "filePath": "/home/dtech/VCF/Blog/zchat/lib/zchat_web/live/user_settings_live.ex",
            "functions": [
              {
                "line": 150,
                "name": "update_password",
                "type": "handle_event",
                "module_name": "ZchatWeb.UserSettingsLive",
                "event_name": "update_password"
              },
              {
                "line": 138,
                "name": "validate_password",
                "type": "handle_event",
                "module_name": "ZchatWeb.UserSettingsLive",
                "event_name": "validate_password"
              },
              {
                "line": 118,
                "name": "update_email",
                "type": "handle_event",
                "module_name": "ZchatWeb.UserSettingsLive",
                "event_name": "update_email"
              },
              {
                "line": 106,
                "name": "validate_email",
                "type": "handle_event",
                "module_name": "ZchatWeb.UserSettingsLive",
                "event_name": "validate_email"
              },
              {
                "line": 89,
                "name": "mount",
                "type": "mount",
                "module_name": "ZchatWeb.UserSettingsLive"
              },
              {
                "line": 76,
                "name": "mount",
                "type": "mount",
                "module_name": "ZchatWeb.UserSettingsLive"
              },
              {
                "line": 6,
                "name": "render",
                "type": "render",
                "module_name": "ZchatWeb.UserSettingsLive"
              }
            ]
          }
        ],
        [
          "/home/dtech/VCF/Blog/zchat/lib/zchat_web/live/user_reset_password_live.ex",
          {
            "module": "ZchatWeb.UserResetPasswordLive",
            "filePath": "/home/dtech/VCF/Blog/zchat/lib/zchat_web/live/user_reset_password_live.ex",
            "functions": [
              {
                "line": 71,
                "name": "validate",
                "type": "handle_event",
                "module_name": "ZchatWeb.UserResetPasswordLive",
                "event_name": "validate"
              },
              {
                "line": 58,
                "name": "reset_password",
                "type": "handle_event",
                "module_name": "ZchatWeb.UserResetPasswordLive",
                "event_name": "reset_password"
              },
              {
                "line": 41,
                "name": "mount",
                "type": "mount",
                "module_name": "ZchatWeb.UserResetPasswordLive"
              },
              {
                "line": 6,
                "name": "render",
                "type": "render",
                "module_name": "ZchatWeb.UserResetPasswordLive"
              }
            ]
          }
        ]
      ],
      "fileHashes": {
        "/home/dtech/VCF/Blog/zchat/lib/zchat_web/live/UI/feed_live.ex": "8c987cc50c8d9c0f689dfb9b864f0cd42327e98c",
        "/home/dtech/VCF/Blog/zchat/lib/zchat_web/live/UI/single_post_live.ex": "7d90654f53d3447fb3730430606f82603a529cf4",
        "/home/dtech/VCF/Blog/zchat/lib/zchat_web/live/create_post_live.ex": "f0e639fac4d959fd03ea488fc9949c5e30464dfc",
        "/home/dtech/VCF/Blog/zchat/lib/zchat_web/live/post_show_live.ex": "8b9d4f266178f86da3fdc911d18e597836263472",
        "/home/dtech/VCF/Blog/zchat/lib/zchat_web/live/user_confirmation_instructions_live.ex": "bc43d0aa10e3c7ca70bf2c16fe31bf7ab6d09ea6",
        "/home/dtech/VCF/Blog/zchat/lib/zchat_web/live/user_forgot_password_live.ex": "4b1bcc061ae9e06a7521d3eafba8d9bc0247c57b",
        "/home/dtech/VCF/Blog/zchat/lib/zchat_web/live/home_live.ex": "7a8fa433e1e4434577f1f3f3c202c7a75072f400",
        "/home/dtech/VCF/Blog/zchat/lib/zchat_web/live/user_confirmation_live.ex": "038c0a4684bfa3e4d3c99170cd8c8f943ea88f00",
        "/home/dtech/VCF/Blog/zchat/lib/zchat_web/live/user_login_live.ex": "dfbc89fa7922ccc22ae6405efb602e8fdf0569a0",
        "/home/dtech/VCF/Blog/zchat/lib/zchat_web/live/user_registration_live.ex": "f583f717ddffe2fdfc36c4cbbd443b959f24457e",
        "/home/dtech/VCF/Blog/zchat/lib/zchat_web/live/user_settings_live.ex": "06e4d05117aa607cb2c9549010640a44ddb68868",
        "/home/dtech/VCF/Blog/zchat/lib/zchat_web/live/user_reset_password_live.ex": "962c5971bc4c3017fe1c87e4c98248931c2b30e6"
      },
      "workspaceRoot": "/home/dtech/VCF/Blog"
    }
  },
  "fileHashes": {}
}